nygen/__init__.py
nygen/__main__.py
nygen/conf.py
nygen/main.py
nygen/lib/__init__.py
nygen/lib/conda.py
nygen/lib/exceptions.py
nygen/lib/formatter.py
nygen/lib/gen.py
nygen/lib/template.py
nygen-0.0.18.dist-info/LICENSE
nygen-0.0.18.dist-info/METADATA
nygen-0.0.18.dist-info/WHEEL
nygen-0.0.18.dist-info/entry_points.txt
nygen-0.0.18.dist-info/top_level.txt
nygen-0.0.18.dist-info/zip-safe
nygen-0.0.18.dist-info/RECORD
