Metadata-Version: 2.1
Name: nygen
Version: 0.0.18
Summary: nygen
Home-page: UNKNOWN
Author: Natalie Fearnley
Author-email: nfearnley@gmail.com
License: MIT
Project-URL: Source, https://github.com/nfearnley/nygen
Project-URL: Tracker, https://github.com/nfearnley/nygen/issues
Platform: any
Classifier: Programming Language :: Python :: 3.9
Classifier: Operating System :: OS Independent
Classifier: License :: OSI Approved :: MIT License
Requires-Python: >=3.9
License-File: LICENSE
Requires-Dist: nygen-default (==0.0.16)
Requires-Dist: nypi (==1.0.1)
Requires-Dist: nconf (==1.1.3)
Requires-Dist: toml (==0.10.2)
Requires-Dist: importlib-metadata (==4.4) ; python_version < "3.10"
Provides-Extra: dev
Requires-Dist: pytest (==6.2.5) ; extra == 'dev'
Requires-Dist: flake8 (==3.9.2) ; extra == 'dev'
Requires-Dist: autopep8 (==1.5.7) ; extra == 'dev'
